[
  { "key": "de", "name": "German", "nativeName": "Deutsch", "version": "1.0.0", "author": "Tribu" },
  { "key": "en", "name": "English", "nativeName": "English", "version": "1.0.0", "author": "Tribu" },
  { "key": "es", "name": "Spanish", "nativeName": "Español", "version": "1.0.0", "author": "Tribu" },
  { "key": "fr", "name": "French", "nativeName": "Français", "version": "1.0.0", "author": "Tribu" },
  { "key": "it", "name": "Italian", "nativeName": "Italiano", "version": "1.0.0", "author": "Tribu" },
  { "key": "nl", "name": "Dutch", "nativeName": "Nederlands", "version": "1.0.0", "author": "Tribu" },
  { "key": "pl", "name": "Polish", "nativeName": "Polski", "version": "1.0.0", "author": "Tribu" },
  { "key": "pt", "name": "Portuguese", "nativeName": "Português", "version": "1.0.0", "author": "Tribu" },
  { "key": "sv", "name": "Swedish", "nativeName": "Svenska", "version": "1.0.0", "author": "Tribu" },
  { "key": "da", "name": "Danish", "nativeName": "Dansk", "version": "1.0.0", "author": "Tribu" },
  { "key": "nb", "name": "Norwegian Bokmål", "nativeName": "Norsk bokmål", "version": "1.0.0", "author": "Tribu" },
  { "key": "fi", "name": "Finnish", "nativeName": "Suomi", "version": "1.0.0", "author": "Tribu" },
  { "key": "cs", "name": "Czech", "nativeName": "Čeština", "version": "1.0.0", "author": "Tribu" },
  { "key": "sk", "name": "Slovak", "nativeName": "Slovenčina", "version": "1.0.0", "author": "Tribu" },
  { "key": "hu", "name": "Hungarian", "nativeName": "Magyar", "version": "1.0.0", "author": "Tribu" },
  { "key": "ro", "name": "Romanian", "nativeName": "Română", "version": "1.0.0", "author": "Tribu" },
  { "key": "el", "name": "Greek", "nativeName": "Ελληνικά", "version": "1.0.0", "author": "Tribu" },
  { "key": "bg", "name": "Bulgarian", "nativeName": "Български", "version": "1.0.0", "author": "Tribu" },
  { "key": "hr", "name": "Croatian", "nativeName": "Hrvatski", "version": "1.0.0", "author": "Tribu" },
  { "key": "sl", "name": "Slovenian", "nativeName": "Slovenščina", "version": "1.0.0", "author": "Tribu" },
  { "key": "lt", "name": "Lithuanian", "nativeName": "Lietuvių", "version": "1.0.0", "author": "Tribu" },
  { "key": "lv", "name": "Latvian", "nativeName": "Latviešu", "version": "1.0.0", "author": "Tribu" },
  { "key": "et", "name": "Estonian", "nativeName": "Eesti", "version": "1.0.0", "author": "Tribu" },
  { "key": "ga", "name": "Irish", "nativeName": "Gaeilge", "version": "1.0.0", "author": "Tribu" }
]
